{"data":{"user":{"name":"Saif Romdhane","bio":"IT Specialist and Software Engineering Student","avatarUrl":"https://avatars.githubusercontent.com/u/130384255?u=47264709dd0af266fc7d0f80ee58eb3c4a2f2d9c&v=4","location":null,"pinnedItems":{"totalCount":6,"edges":[{"node":{"name":"Trash-Classification-Flutter-Application","description":"This is my submition for a challenge in TWISE NIGHT Challenge 2025 using Flutter and AI","forkCount":0,"stargazers":{"totalCount":1},"url":"https://github.com/SaifRomdhaneTN/Trash-Classification-Flutter-Application","id":"R_kgDON2IgtA","diskUsage":233553,"primaryLanguage":{"name":"Python","color":"#3572A5"}}},{"node":{"name":"assembly-endgame","description":null,"forkCount":0,"stargazers":{"totalCount":0},"url":"https://github.com/SaifRomdhaneTN/assembly-endgame","id":"R_kgDOPhwk-w","diskUsage":38,"primaryLanguage":{"name":"JavaScript","color":"#f1e05a"}}},{"node":{"name":"Backend-sw","description":null,"forkCount":0,"stargazers":{"totalCount":0},"url":"https://github.com/SaifRomdhaneTN/Backend-sw","id":"R_kgDOPmVkLw","diskUsage":106,"primaryLanguage":{"name":"PHP","color":"#4F5D95"}}},{"node":{"name":"ChefClaude","description":null,"forkCount":0,"stargazers":{"totalCount":0},"url":"https://github.com/SaifRomdhaneTN/ChefClaude","id":"R_kgDOPf7lXw","diskUsage":56,"primaryLanguage":{"name":"JavaScript","color":"#f1e05a"}}},{"node":{"name":"Food-Doctor","description":"Food doctor app created using Flutter and Firebase ","forkCount":0,"stargazers":{"totalCount":0},"url":"https://github.com/SaifRomdhaneTN/Food-Doctor","id":"R_kgDOJVAX8w","diskUsage":22671,"primaryLanguage":{"name":"Dart","color":"#00B4AB"}}},{"node":{"name":"frontend-sw","description":null,"forkCount":0,"stargazers":{"totalCount":0},"url":"https://github.com/SaifRomdhaneTN/frontend-sw","id":"R_kgDOPmVhyg","diskUsage":188,"primaryLanguage":{"name":"TypeScript","color":"#3178c6"}}}]}}}}